openepd/__init__.py
openepd/__version__.py
openepd/api/__init__.py
openepd/api/average_dataset/__init__.py
openepd/api/average_dataset/generic_estimate_sync_api.py
openepd/api/average_dataset/industry_epd_sync_api.py
openepd/api/base_sync_client.py
openepd/api/category/__init__.py
openepd/api/category/dto.py
openepd/api/category/sync_api.py
openepd/api/common.py
openepd/api/dto/__init__.py
openepd/api/dto/base.py
openepd/api/dto/common.py
openepd/api/dto/meta.py
openepd/api/dto/mf.py
openepd/api/dto/params.py
openepd/api/epd/__init__.py
openepd/api/epd/dto.py
openepd/api/epd/sync_api.py
openepd/api/errors.py
openepd/api/org/__init__.py
openepd/api/org/sync_api.py
openepd/api/pcr/__init__.py
openepd/api/pcr/sync_api.py
openepd/api/plant/__init__.py
openepd/api/plant/sync_api.py
openepd/api/standard/__init__.py
openepd/api/standard/sync_api.py
openepd/api/sync_client.py
openepd/api/test/__init__.py
openepd/api/utils.py
openepd/bundle/__init__.py
openepd/bundle/base.py
openepd/bundle/model.py
openepd/bundle/reader.py
openepd/bundle/writer.py
openepd/category/__init__.py
openepd/category/base.py
openepd/category/generated.py
openepd/category/search.py
openepd/constants/__init__.py
openepd/constants/scope_phases.py
openepd/m49/__init__.py
openepd/m49/const.py
openepd/m49/tree.py
openepd/m49/utils.py
openepd/model/__init__.py
openepd/model/base.py
openepd/model/category.py
openepd/model/category_meta.py
openepd/model/common.py
openepd/model/declaration.py
openepd/model/epd.py
openepd/model/factory.py
openepd/model/generic_estimate.py
openepd/model/geography.py
openepd/model/industry_epd.py
openepd/model/lcia.py
openepd/model/light/__init__.py
openepd/model/light/epd.py
openepd/model/light/factory.py
openepd/model/light/generic_estimate.py
openepd/model/light/industry_epd.py
openepd/model/org.py
openepd/model/pcr.py
openepd/model/resource.py
openepd/model/specs/README.md
openepd/model/specs/__init__.py
openepd/model/specs/asphalt.py
openepd/model/specs/base.py
openepd-7.21.0.dist-info/LICENSE
openepd-7.21.0.dist-info/METADATA
openepd-7.21.0.dist-info/WHEEL
openepd-7.21.0.dist-info/RECORD
