Metadata-Version: 2.3
Name: openepd
Version: 7.21.0
Summary: Python library to work with OpenEPD format
License: Apache-2.0
Author: C-Change Labs
Author-email: support@c-change-labs.com
Maintainer: C-Change Labs
Maintainer-email: open-source@c-change-labs.com
Requires-Python: >=3.11,<4.0
Classifier: Development Status :: 4 - Beta
Classifier: Intended Audience :: Developers
Classifier: License :: OSI Approved :: Apache Software License
Classifier: Operating System :: OS Independent
Classifier: Programming Language :: Python :: 3
Classifier: Programming Language :: Python :: 3.11
Classifier: Programming Language :: Python :: 3.12
Classifier: Programming Language :: Python :: 3.13
Classifier: Topic :: Software Development :: Libraries :: Python Modules
Provides-Extra: api-client
Requires-Dist: email-validator (>=1.3.1)
Requires-Dist: idna (>=3.7)
Requires-Dist: open-xpd-uuid (>=0.2.1,<2)
Requires-Dist: openlocationcode (>=1.0.1)
Requires-Dist: pydantic (>=2.0,<3)
Requires-Dist: requests (>=2.0) ; extra == "api-client"
Project-URL: Repository, https://github.com/cchangelabs/openepd
